atts/__init__.py
atts/auto_test_splitter.py
atts-0.0.8.dist-info/LICENSE.txt
atts-0.0.8.dist-info/METADATA
atts-0.0.8.dist-info/WHEEL
atts-0.0.8.dist-info/top_level.txt
atts-0.0.8.dist-info/RECORD
