Metadata-Version: 2.1
Name: atts
Version: 0.0.8
Summary: Train_test splitter with adversarial validation
Home-page: https://github.com/alikula314/att_split
Author: Muhammet Ali Kula
Author-email: alikula3.14@gmail.com
License: MIT
Keywords: adversarial validation train-test-split data-sceince machine-learning
Platform: UNKNOWN
Classifier: Development Status :: 4 - Beta
Classifier: Intended Audience :: Developers
Classifier: License :: OSI Approved :: MIT License
Classifier: Programming Language :: Python :: 3
License-File: LICENSE.txt
Requires-Dist: pandas
Requires-Dist: numpy
Requires-Dist: seaborn
Requires-Dist: matplotlib
Requires-Dist: roc-auc-score
Requires-Dist: train-test-split
Requires-Dist: xgboost
Requires-Dist: cv
Requires-Dist: plotly
Requires-Dist: plotly.express
